setup.py
g3py/__init__.py
g3py/config.py
g3py/models.py
g3py.egg-info/PKG-INFO
g3py.egg-info/SOURCES.txt
g3py.egg-info/dependency_links.txt
g3py.egg-info/not-zip-safe
g3py.egg-info/requires.txt
g3py.egg-info/top_level.txt
g3py/data/__init__.py
g3py/functions/__init__.py
g3py/functions/hypers.py
g3py/functions/kernels.py
g3py/functions/mappings.py
g3py/functions/means.py
g3py/functions/metrics.py
g3py/libs/__init__.py
g3py/libs/data.py
g3py/libs/experiments.py
g3py/libs/plots.py
g3py/libs/tensors.py
g3py/libs/traces.py
g3py/processes/__init__.py
g3py/processes/gaussian.py
g3py/processes/stochastic.py
g3py/processes/studentT.py
g3py/sandbox/__init__.py
g3py/sandbox/gpmm.py
g3py/sandbox/tgp.py
g3py/sandbox/traces.py