Metadata-Version: 1.0
Name: g3py
Version: 0.2.4.9
Summary: Generalized Graphical Gaussian Processes
Home-page: https://github.com/griosd/g3py
Author: Gonzalo Rios
Author-email: grios@dim.uchile.cl
License: MIT
Platform: UNKNOWN
